book/filtering/adaptive_resampling.py
book/filtering/comparing_bootstrap_guided_apf_lingauss.py
book/filtering/comparing_bootstrap_guided_apf_stochvol.py
book/filtering/neurodecoding.py
book/kalman/check_kalman.py
book/mcmc/compare_mcmc_samplers_stochvol.py
book/mle/compare_smc_sqmc_malik_and_pitt.py
book/mle/contour_loglik_ecological.py
book/mle/contour_loglik_stochvol.py
book/mle/hurzeler_kunsch.py
book/mle/malikpitt_interpolation.py
book/mle/mle_neuro.py
book/mle/variability_loglik_estimates.py
book/pmcmc/pgibbs_ecological.py
book/pmcmc/pmmh_biased_lingauss.py
book/pmcmc/pmmh_cost.py
book/pmcmc/pmmh_lingauss.py
book/pmcmc/pmmh_lingauss_varying_scale.py
book/resampling/compare_cpu_time_resampling.py
book/resampling/compare_tv_distance_resampling.py
book/smc2/smc2_stochvol_leverage.py
book/smc_samplers/logistic_reg.py
book/smoothing/offline_smoothing.py
book/smoothing/online_smoothing.py
book/smoothing/plot_genealogy.py
book/sqmc/sqmc_as_dim_grows.py
book/sqmc/sqmc_gordon.py
docs/source/conf.py
papers/binarySMC/boston.py
papers/binarySMC/concrete.py
papers/binarySMC/lost_time.py
papers/complexity_smoothing/ffbs_cox_model.py
papers/complexity_smoothing/hybrid_paris.py
papers/complexity_smoothing/mle_neuro.py
papers/complexity_smoothing/mle_neuro_nrsteps.py
papers/complexity_smoothing/nr_mcmc_steps.py
papers/mirror/tempered_ibis.py
papers/nested/tempering_vs_nested_logistic.py
papers/nested/vanilla_nested_logistic.py
papers/wastefreeSMC/logistic.py
papers/wastefreeSMC/variance_estimates_fixed_tempering.py
papers/wastefreeSMC/variance_estimates_ibis.py
papers/wastefreeSMC/variance_estimates_tempering.py
particles/__init__.py
particles/binary_smc.py
particles/collectors.py
particles/core.py
particles/datasets.py
particles/distributions.py
particles/hilbert.py
particles/hmm.py
particles/kalman.py
particles/mcmc.py
particles/nested.py
particles/resampling.py
particles/rqmc.py
particles/smc_samplers.py
particles/smoothing.py
particles/state_space_models.py
particles-0.4.dist-info/LICENSE
particles-0.4.dist-info/METADATA
particles-0.4.dist-info/WHEEL
particles-0.4.dist-info/top_level.txt
particles-0.4.dist-info/RECORD
