Metadata-Version: 2.1
Name: particles
Version: 0.4
Summary: Sequential Monte Carlo in Python
Author-email: Nicolas Chopin <nicolas.chopin@ensae.fr>
License: MIT License
Project-URL: repository, https://github.com/nchopin/particles
Project-URL: documentation, https://particles-sequential-monte-carlo-in-python.readthedocs.io/en/latest/
Classifier: Programming Language :: Python
Classifier: Development Status :: 3 - Alpha
Classifier: Natural Language :: English
Classifier: Environment :: Console
Classifier: Intended Audience :: Science/Research
Classifier: License :: OSI Approved :: MIT License
Classifier: Operating System :: OS Independent
Classifier: Topic :: Scientific/Engineering :: Mathematics
Requires-Python: >=3.9
License-File: LICENSE
Requires-Dist: joblib
Requires-Dist: numba
Requires-Dist: numpy <2,>=1.18
Requires-Dist: scipy >=1.7
Requires-Dist: scikit-learn
Provides-Extra: docs
Requires-Dist: sphinx ==7.0.1 ; extra == 'docs'
Requires-Dist: nbsphinx ==0.9.2 ; extra == 'docs'
Provides-Extra: extra
Requires-Dist: pandas ; extra == 'extra'
Requires-Dist: statsmodels ; extra == 'extra'
Requires-Dist: ipython ; extra == 'extra'
Requires-Dist: seaborn ; extra == 'extra'
Requires-Dist: matplotlib ; extra == 'extra'
